cumtd/__init__.py
cumtd/cumtd_client.py
cumtd_python-1.0.0.dist-info/DESCRIPTION.rst
cumtd_python-1.0.0.dist-info/METADATA
cumtd_python-1.0.0.dist-info/RECORD
cumtd_python-1.0.0.dist-info/WHEEL
cumtd_python-1.0.0.dist-info/metadata.json
cumtd_python-1.0.0.dist-info/top_level.txt
